numerical_solution/__init__.py
numerical_solution/main.py
numerical_solution-0.1.0.dist-info/METADATA
numerical_solution-0.1.0.dist-info/WHEEL
numerical_solution-0.1.0.dist-info/top_level.txt
numerical_solution-0.1.0.dist-info/RECORD
