Metadata-Version: 2.4
Name: numerical_solution
Version: 0.1.0
Summary: Numerical Methods library 
Author: Eshayat Zamil Sharaf
Author-email: imsharaf10@gmail.com
License: MIT
Requires-Python: >=3.8
Requires-Dist: numpy
Requires-Dist: pandas
Requires-Dist: matplotlib
Requires-Dist: seaborn
Requires-Dist: tqdm
Requires-Dist: sympy
Dynamic: author
Dynamic: author-email
Dynamic: description-content-type
Dynamic: license
Dynamic: requires-dist
Dynamic: requires-python
Dynamic: summary
